Csv2Xml.py
Csv2Xml-0.0.1.dist-info/LICENSE.txt
Csv2Xml-0.0.1.dist-info/METADATA
Csv2Xml-0.0.1.dist-info/WHEEL
Csv2Xml-0.0.1.dist-info/top_level.txt
Csv2Xml-0.0.1.dist-info/RECORD
