Metadata-Version: 2.1
Name: Csv2Xml
Version: 0.0.1
Summary: Csv2Xml is a libary used to convert a CSV(comma-separated values) file to XML(extensible markup language).
Home-page: https://github.com/suraj1709
Author: Suraj Kumar Dey
Author-email: surajdey8603@gmail.com
License: UNKNOWN
Platform: UNKNOWN
Classifier: Programming Language :: Python :: 3
Classifier: License :: OSI Approved :: MIT License
Classifier: Operating System :: OS Independent
Requires-Dist: Pandas
